LICENSE
MANIFEST.in
README.md
pyproject.toml
setup.py
pyrdpdb.egg-info/PKG-INFO
pyrdpdb.egg-info/SOURCES.txt
pyrdpdb.egg-info/dependency_links.txt
pyrdpdb.egg-info/entry_points.txt
pyrdpdb.egg-info/not-zip-safe
pyrdpdb.egg-info/requires.txt
pyrdpdb.egg-info/top_level.txt
pyrdpdb/aiordp/__init__.py
pyrdpdb/aiordp/_compat.py
pyrdpdb/aiordp/_socketio.py
pyrdpdb/aiordp/_version.py
pyrdpdb/aiordp/charset.py
pyrdpdb/aiordp/connections.py
pyrdpdb/aiordp/converters.py
pyrdpdb/aiordp/cursors.py
pyrdpdb/aiordp/err.py
pyrdpdb/aiordp/logger.py
pyrdpdb/aiordp/pool.py
pyrdpdb/aiordp/utils.py
pyrdpdb/aiordp/wireline_protocol.py
pyrdpdb/aiordp/constants/COMMAND.py
pyrdpdb/aiordp/constants/CONSTANTS.py
pyrdpdb/aiordp/constants/CR.py
pyrdpdb/aiordp/constants/ER.py
pyrdpdb/aiordp/constants/FIELD_TYPE.py
pyrdpdb/aiordp/constants/FLAG.py
pyrdpdb/aiordp/constants/__init__.py
pyrdpdb/aiordp/example/__init__.py
pyrdpdb/aiordp/example/dbapi_cursor.py
pyrdpdb/aiordp/example/engine.py
pyrdpdb/aiordp/example/many.py
pyrdpdb/aiordp/example/simple_sa.py
pyrdpdb/aiordp/sa/__init__.py
pyrdpdb/aiordp/sa/asyncrapids.py
pyrdpdb/aiordp/sa/base.py
pyrdpdb/aiordp/sa/connection.py
pyrdpdb/aiordp/sa/engine.py
pyrdpdb/aiordp/sa/exc.py
pyrdpdb/aiordp/sa/result.py
pyrdpdb/aiordp/sa/types.py
pyrdpdb/messages/__init__.py
pyrdpdb/messages/compatibility/__init__.py
pyrdpdb/messages/compatibility/MessageTypes/__init__.py
pyrdpdb/messages/compatibility/MessageTypes/constants.py
pyrdpdb/messages/compatibility/MessageTypes/ttypes.py
pyrdpdb/messages/compatibility/ProtocolCompatibleRequest/__init__.py
pyrdpdb/messages/compatibility/ProtocolCompatibleRequest/constants.py
pyrdpdb/messages/compatibility/ProtocolCompatibleRequest/ttypes.py
pyrdpdb/messages/compatibility/ProtocolCompatibleResponse/__init__.py
pyrdpdb/messages/compatibility/ProtocolCompatibleResponse/constants.py
pyrdpdb/messages/compatibility/ProtocolCompatibleResponse/ttypes.py
pyrdpdb/messages/compatibility/ProtocolIncompatibleResponse/__init__.py
pyrdpdb/messages/compatibility/ProtocolIncompatibleResponse/constants.py
pyrdpdb/messages/compatibility/ProtocolIncompatibleResponse/ttypes.py
pyrdpdb/messages/v2/__init__.py
