Metadata-Version: 2.1
Name: pyrdpdb
Version: 4.2.0
Summary: Pure Python RapidsDB Driver
Home-page: UNKNOWN
Author: Robert Li
Author-email: robert.li@boraydata.com
License: MIT
Platform: UNKNOWN
Classifier: Programming Language :: Python :: 3.9
Classifier: Topic :: Database
Classifier: License :: OSI Approved :: MIT License
Classifier: Operating System :: OS Independent
Requires-Python: >=3.9
License-File: LICENSE
